pypi_chat-0.0.4.dist-info/METADATA
pypi_chat-0.0.4.dist-info/RECORD
pypi_chat-0.0.4.dist-info/WHEEL
pypi_chat-0.0.4.dist-info/entry_points.txt
pypi_chat-0.0.4.dist-info/top_level.txt
pypi_client/__init__.py
pypi_client/main.py
pypi_client/test_client.py
pypi_client/accounts/__init__.py
pypi_client/accounts/account.py
pypi_client/accounts/db/__init__.py
pypi_client/accounts/db/models.py
pypi_client/accounts/db/settings.py
pypi_client/core/__init__.py
pypi_client/core/client.py
pypi_client/core/handlers.py
pypi_client/protocol/__init__.py
pypi_client/protocol/jim.py
pypi_client/ui/__init__.py
pypi_client/ui/acc_settings.py
pypi_client/ui/dialogs.py
pypi_client/ui/gui_class.py
pypi_client/ui/img/add_icon.png
pypi_client/ui/img/icon.png
pypi_client/ui/img/yang.png
pypi_client/ui/ui_files/__init__.py
pypi_client/ui/ui_files/about_ui.py
pypi_client/ui/ui_files/acc_set_ui.py
pypi_client/ui/ui_files/client_ui.py
pypi_client/ui/ui_files/enter_ui.py
pypi_client/ui/ui_files/help_ui.py
pypi_client/utils/__init__.py
pypi_client/utils/decorators.py
pypi_client/utils/log_config.py
pypi_client/utils/utils.py
